MaFx/CONSTANTS.py
MaFx/__init__.py
MaFx-0.0.2.dist-info/METADATA
MaFx-0.0.2.dist-info/WHEEL
MaFx-0.0.2.dist-info/top_level.txt
MaFx-0.0.2.dist-info/RECORD
