Metadata-Version: 2.1
Name: MaFx
Version: 0.0.2
Summary: A Complex Math Library
Author: FedxD
Author-email: abbaskazim135@gmail.com
License: MIT
